<?xml version="1.0"?>
<TermStores>
    	<TermStore Name="Managed Metadata Service" IsOnline="True" WorkingLanguage="1033" DefaultLanguage="1033" SystemGroup="c6fb3e37-0997-42b1-8e3c-2706a36adbc4">
    		<Groups>
    		<Group Id="ecf2098a-ae61-4044-844f-6f31b9983063" Name="Banque de termes - CFSJ" Description="" IsSystemGroup="False" IsSiteCollectionGroup="False">
	    			<TermSets><TermSet Id="88392e22-4524-419e-af46-b1c7ee481b0c" Name="Lieu" Description="Un lieu (au pluriel : lieux) désigne une portion de l'espace, au sens propre ou au sens figuré, caractérisée par son usage ou par les évènements qui s'y sont déroulés. " Contact="" IsAvailableForTagging="True" IsOpenForTermCreation="True" CustomSortOrder="False"><CustomProperties></CustomProperties>
		    				<Terms><Term Id="96f8025e-03d0-460c-8cb2-20596528204a" Name="Corporation du Fort St-Jean" IsDeprecated="False" IsAvailableForTagging="True" IsKeyword="False" IsReused="False" IsRoot="True" IsSourceTerm="True" CustomSortOrder="False"><Descriptions><Description Language="1033" Value="" /></Descriptions><CustomProperties></CustomProperties><LocalCustomProperties></LocalCustomProperties><Labels><Label Value="Corporation du Fort St-Jean" Language="1036" IsDefaultForLanguage="True" /></Labels><Terms><Term Id="1301af2b-0cd0-4a55-ad41-11753a16917e" Name="Ave Carleton" IsDeprecated="False" IsAvailableForTagging="True" IsKeyword="False" IsReused="False" IsRoot="False" IsSourceTerm="True" CustomSortOrder="False"><Descriptions><Description Language="1033" Value="" /></Descriptions><CustomProperties></CustomProperties><LocalCustomProperties></LocalCustomProperties><Labels><Label Value="Ave Carleton" Language="1036" IsDefaultForLanguage="True" /></Labels><Terms><Term Id="06dfc827-b1be-4453-b44b-359db8e220d5" Name="Marina" IsDeprecated="False" IsAvailableForTagging="True" IsKeyword="False" IsReused="False" IsRoot="False" IsSourceTerm="True" CustomSortOrder="False"><Descriptions><Description Language="1033" Value="C124 (9502) Marina" /></Descriptions><CustomProperties></CustomProperties><LocalCustomProperties></LocalCustomProperties><Labels><Label Value="Marina" Language="1036" IsDefaultForLanguage="True" /><Label Value="C124" Language="1036" IsDefaultForLanguage="False" /></Labels><Terms></Terms></Term></Terms></Term><Term Id="4c164561-2eaa-4ff0-bad7-3b7a4f5aa6af" Name="Ave Iberville" IsDeprecated="False" IsAvailableForTagging="True" IsKeyword="False" IsReused="False" IsRoot="False" IsSourceTerm="True" CustomSortOrder="False"><Descriptions><Description Language="1033" Value="" /></Descriptions><CustomProperties></CustomProperties><LocalCustomProperties></LocalCustomProperties><Labels><Label Value="Ave Iberville" Language="1036" IsDefaultForLanguage="True" /></Labels><Terms></Terms></Term><Term Id="d1f417ff-9afd-457e-8edd-6777f71ff1fe" Name="Ave Leicester" IsDeprecated="False" IsAvailableForTagging="True" IsKeyword="False" IsReused="False" IsRoot="False" IsSourceTerm="True" CustomSortOrder="False"><Descriptions><Description Language="1033" Value="" /></Descriptions><CustomProperties></CustomProperties><LocalCustomProperties></LocalCustomProperties><Labels><Label Value="Ave Leicester" Language="1036" IsDefaultForLanguage="True" /></Labels><Terms><Term Id="95c53e16-4668-482f-ab28-f6cae873c186" Name="Pavillon De Lery" IsDeprecated="False" IsAvailableForTagging="True" IsKeyword="False" IsReused="False" IsRoot="False" IsSourceTerm="True" CustomSortOrder="False"><Descriptions><Description Language="1033" Value="C109 (8801) Pavillon De Lery (Academie)" /></Descriptions><CustomProperties></CustomProperties><LocalCustomProperties></LocalCustomProperties><Labels><Label Value="Pavillon De Lery" Language="1036" IsDefaultForLanguage="True" /></Labels><Terms><Term Id="3ac06105-e3e6-4b57-8591-b2192e0a3057" Name="Entrepôt de produits chimiques" IsDeprecated="False" IsAvailableForTagging="True" IsKeyword="False" IsReused="False" IsRoot="False" IsSourceTerm="True" CustomSortOrder="False"><Descriptions><Description Language="1033" Value="C126 (8803) Entrepôt de produits chimiques sud C109" /></Descriptions><CustomProperties></CustomProperties><LocalCustomProperties></LocalCustomProperties><Labels><Label Value="Entrepôt de produits chimiques" Language="1036" IsDefaultForLanguage="True" /><Label Value="C109" Language="1036" IsDefaultForLanguage="False" /></Labels><Terms></Terms></Term></Terms></Term><Term Id="b227d76b-de2d-4574-b952-03cb3e92ceb3" Name="Pavillon Lahaie" IsDeprecated="False" IsAvailableForTagging="True" IsKeyword="False" IsReused="False" IsRoot="False" IsSourceTerm="True" CustomSortOrder="False"><Descriptions><Description Language="1033" Value="C125 (8802) Pavillon Lahaie (Bibliothèque)" /></Descriptions><CustomProperties></CustomProperties><LocalCustomProperties></LocalCustomProperties><Labels><Label Value="Pavillon Lahaie" Language="1036" IsDefaultForLanguage="True" /><Label Value="C125" Language="1036" IsDefaultForLanguage="False" /><Label Value="Lahaie" Language="1036" IsDefaultForLanguage="False" /></Labels><Terms></Terms></Term></Terms></Term><Term Id="967a43c6-0521-4b7d-b430-4497cf4da83b" Name="Ave Royal Roussillon" IsDeprecated="False" IsAvailableForTagging="True" IsKeyword="False" IsReused="False" IsRoot="False" IsSourceTerm="True" CustomSortOrder="False"><Descriptions><Description Language="1033" Value="" /></Descriptions><CustomProperties></CustomProperties><LocalCustomProperties></LocalCustomProperties><Labels><Label Value="Ave Royal Roussillon" Language="1036" IsDefaultForLanguage="True" /></Labels><Terms><Term Id="80dc1f1f-f63d-47ee-836f-71b872f92d5d" Name="Pavilllon Couture" IsDeprecated="False" IsAvailableForTagging="True" IsKeyword="False" IsReused="False" IsRoot="False" IsSourceTerm="True" CustomSortOrder="False"><Descriptions><Description Language="1033" Value="C016 (3001) Pavillon Couture" /></Descriptions><CustomProperties></CustomProperties><LocalCustomProperties></LocalCustomProperties><Labels><Label Value="Pavilllon Couture" Language="1036" IsDefaultForLanguage="True" /><Label Value="C16" Language="1036" IsDefaultForLanguage="False" /><Label Value="Couture" Language="1036" IsDefaultForLanguage="False" /></Labels><Terms></Terms></Term></Terms></Term><Term Id="a32a426b-1f00-4171-a8fd-e2aa6797b47f" Name="Boul Carignan-Salières" IsDeprecated="False" IsAvailableForTagging="True" IsKeyword="False" IsReused="False" IsRoot="False" IsSourceTerm="True" CustomSortOrder="False"><Descriptions><Description Language="1033" Value="" /></Descriptions><CustomProperties></CustomProperties><LocalCustomProperties></LocalCustomProperties><Labels><Label Value="Boul Carignan-Salières" Language="1036" IsDefaultForLanguage="True" /></Labels><Terms><Term Id="d48c55ff-0358-4287-85c7-679265260e9e" Name="C20" IsDeprecated="False" IsAvailableForTagging="True" IsKeyword="False" IsReused="False" IsRoot="False" IsSourceTerm="True" CustomSortOrder="False"><Descriptions><Description Language="1033" Value="C020 (4801) Entrepôt, Approvisionnement, Tailleur" /></Descriptions><CustomProperties></CustomProperties><LocalCustomProperties></LocalCustomProperties><Labels><Label Value="C20" Language="1036" IsDefaultForLanguage="True" /><Label Value="Appro" Language="1036" IsDefaultForLanguage="False" /><Label Value="C020" Language="1036" IsDefaultForLanguage="False" /></Labels><Terms></Terms></Term><Term Id="2da93b37-6b5c-4765-b80b-14786514be2f" Name="Guérite" IsDeprecated="False" IsAvailableForTagging="True" IsKeyword="False" IsReused="False" IsRoot="False" IsSourceTerm="True" CustomSortOrder="False"><Descriptions><Description Language="1033" Value="C103 (2601) Guérite" /></Descriptions><CustomProperties></CustomProperties><LocalCustomProperties></LocalCustomProperties><Labels><Label Value="Guérite" Language="1036" IsDefaultForLanguage="True" /><Label Value="Entré" Language="1036" IsDefaultForLanguage="False" /></Labels><Terms></Terms></Term><Term Id="6e42e97e-d553-410a-af81-96501f0f6b9a" Name="Pavillon Cartier" IsDeprecated="False" IsAvailableForTagging="True" IsKeyword="False" IsReused="False" IsRoot="False" IsSourceTerm="True" CustomSortOrder="False"><Descriptions><Description Language="1033" Value="C108 (6803) PAVILLON CARTIER" /></Descriptions><CustomProperties></CustomProperties><LocalCustomProperties></LocalCustomProperties><Labels><Label Value="Pavillon Cartier" Language="1036" IsDefaultForLanguage="True" /><Label Value="C108" Language="1036" IsDefaultForLanguage="False" /><Label Value="Cartier" Language="1036" IsDefaultForLanguage="False" /></Labels><Terms></Terms></Term><Term Id="c9219b00-44b9-4c3f-9dab-74c81783a4f0" Name="PAVILLON CHAMPLAIN" IsDeprecated="False" IsAvailableForTagging="True" IsKeyword="False" IsReused="False" IsRoot="False" IsSourceTerm="True" CustomSortOrder="False"><Descriptions><Description Language="1033" Value="C107 (6802) PAVILLON CHAMPLAIN" /></Descriptions><CustomProperties></CustomProperties><LocalCustomProperties></LocalCustomProperties><Labels><Label Value="PAVILLON CHAMPLAIN" Language="1036" IsDefaultForLanguage="True" /><Label Value="C107" Language="1036" IsDefaultForLanguage="False" /><Label Value="Champlain" Language="1036" IsDefaultForLanguage="False" /></Labels><Terms></Terms></Term><Term Id="1032eba0-3207-4aa5-b77c-e972f3c78f58" Name="PAVILLON MAISONNEUVE" IsDeprecated="False" IsAvailableForTagging="True" IsKeyword="False" IsReused="False" IsRoot="False" IsSourceTerm="True" CustomSortOrder="False"><Descriptions><Description Language="1033" Value="C013 (6801) PAVILLON MAISONNEUVE" /></Descriptions><CustomProperties></CustomProperties><LocalCustomProperties></LocalCustomProperties><Labels><Label Value="PAVILLON MAISONNEUVE" Language="1036" IsDefaultForLanguage="True" /><Label Value="C013" Language="1036" IsDefaultForLanguage="False" /><Label Value="Maisonneuve" Language="1036" IsDefaultForLanguage="False" /></Labels><Terms></Terms></Term><Term Id="97d39742-f500-48f7-852c-831d9055bbb0" Name="Pavillon Vanier" IsDeprecated="False" IsAvailableForTagging="True" IsKeyword="False" IsReused="False" IsRoot="False" IsSourceTerm="True" CustomSortOrder="False"><Descriptions><Description Language="1033" Value="C116 (8901) PAVILLON VANIER (COMPLEXE SPORTIF)&#xA;" /></Descriptions><CustomProperties></CustomProperties><LocalCustomProperties></LocalCustomProperties><Labels><Label Value="Pavillon Vanier" Language="1036" IsDefaultForLanguage="True" /></Labels><Terms></Terms></Term><Term Id="de215e34-cdff-4ac6-9521-d6d3a2277b16" Name="St-Maurice" IsDeprecated="False" IsAvailableForTagging="True" IsKeyword="False" IsReused="False" IsRoot="False" IsSourceTerm="True" CustomSortOrder="False"><Descriptions><Description Language="1033" Value="C104 (1001) ST-MAURICE (CHAPELLE CATHOLIQUE)" /></Descriptions><CustomProperties></CustomProperties><LocalCustomProperties></LocalCustomProperties><Labels><Label Value="St-Maurice" Language="1036" IsDefaultForLanguage="True" /><Label Value="C104" Language="1036" IsDefaultForLanguage="False" /><Label Value="Chapelle" Language="1036" IsDefaultForLanguage="False" /></Labels><Terms></Terms></Term></Terms></Term><Term Id="2aa9d1d3-c58f-46a4-9a2c-0a658b06aaee" Name="Boul de Peupliers" IsDeprecated="False" IsAvailableForTagging="True" IsKeyword="False" IsReused="False" IsRoot="False" IsSourceTerm="True" CustomSortOrder="False"><Descriptions><Description Language="1033" Value="" /></Descriptions><CustomProperties></CustomProperties><LocalCustomProperties></LocalCustomProperties><Labels><Label Value="Boul de Peupliers" Language="1036" IsDefaultForLanguage="True" /></Labels><Terms><Term Id="bb3353ee-a1d3-4a12-b429-c46bec11e964" Name="Garage" IsDeprecated="False" IsAvailableForTagging="True" IsKeyword="False" IsReused="False" IsRoot="False" IsSourceTerm="True" CustomSortOrder="False"><Descriptions><Description Language="1033" Value="" /></Descriptions><CustomProperties></CustomProperties><LocalCustomProperties></LocalCustomProperties><Labels><Label Value="Garage" Language="1036" IsDefaultForLanguage="True" /></Labels><Terms></Terms></Term><Term Id="d96c298d-8474-4a0f-a92c-796ddecba572" Name="POMPAGE DES EAUX PLUVIALES" IsDeprecated="False" IsAvailableForTagging="True" IsKeyword="False" IsReused="False" IsRoot="False" IsSourceTerm="True" CustomSortOrder="False"><Descriptions><Description Language="1033" Value="C110 (2001) POMPAGE DES EAUX PLUVIALES" /></Descriptions><CustomProperties></CustomProperties><LocalCustomProperties></LocalCustomProperties><Labels><Label Value="POMPAGE DES EAUX PLUVIALES" Language="1036" IsDefaultForLanguage="True" /><Label Value="C110" Language="1036" IsDefaultForLanguage="False" /></Labels><Terms></Terms></Term><Term Id="dff99611-27e8-4e1b-96b2-23bc91782e18" Name="Résidence 1" IsDeprecated="False" IsAvailableForTagging="True" IsKeyword="False" IsReused="False" IsRoot="False" IsSourceTerm="True" CustomSortOrder="False"><Descriptions><Description Language="1033" Value="C115 (7012) Résidence 1&#xA;Maison du Commandant ou dignitaire" /></Descriptions><CustomProperties></CustomProperties><LocalCustomProperties></LocalCustomProperties><Labels><Label Value="Résidence 1" Language="1036" IsDefaultForLanguage="True" /><Label Value="C115" Language="1036" IsDefaultForLanguage="False" /><Label Value="Maison du Commandant" Language="1036" IsDefaultForLanguage="False" /></Labels><Terms></Terms></Term><Term Id="3cef5f90-7527-443a-98a3-5e286113f704" Name="Résidence 3" IsDeprecated="False" IsAvailableForTagging="True" IsKeyword="False" IsReused="False" IsRoot="False" IsSourceTerm="True" CustomSortOrder="False"><Descriptions><Description Language="1033" Value="C119 (7013) Résidence 3" /></Descriptions><CustomProperties></CustomProperties><LocalCustomProperties></LocalCustomProperties><Labels><Label Value="Résidence 3" Language="1036" IsDefaultForLanguage="True" /><Label Value="C119" Language="1036" IsDefaultForLanguage="False" /><Label Value="Maison 3" Language="1036" IsDefaultForLanguage="False" /></Labels><Terms></Terms></Term></Terms></Term><Term Id="a6bdd91a-68c0-40f3-a228-5217ba407d5c" Name="Carré historique" IsDeprecated="False" IsAvailableForTagging="True" IsKeyword="False" IsReused="False" IsRoot="False" IsSourceTerm="True" CustomSortOrder="False"><Descriptions><Description Language="1033" Value="" /></Descriptions><CustomProperties></CustomProperties><LocalCustomProperties></LocalCustomProperties><Labels><Label Value="Carré historique" Language="1036" IsDefaultForLanguage="True" /></Labels><Terms><Term Id="17fea832-3bf9-48c9-ad06-600c99243518" Name="P5" IsDeprecated="False" IsAvailableForTagging="True" IsKeyword="False" IsReused="False" IsRoot="False" IsSourceTerm="True" CustomSortOrder="False"><Descriptions><Description Language="1033" Value="" /></Descriptions><CustomProperties></CustomProperties><LocalCustomProperties></LocalCustomProperties><Labels><Label Value="P5" Language="1036" IsDefaultForLanguage="True" /></Labels><Terms></Terms></Term><Term Id="56188867-fdb3-4cf7-8f9c-ea7df6238a20" Name="Pavillon Galissonière" IsDeprecated="False" IsAvailableForTagging="True" IsKeyword="False" IsReused="False" IsRoot="False" IsSourceTerm="True" CustomSortOrder="False"><Descriptions><Description Language="1033" Value="C006 (8202) Pavillon La Galissonière" /></Descriptions><CustomProperties></CustomProperties><LocalCustomProperties></LocalCustomProperties><Labels><Label Value="Pavillon Galissonière" Language="1036" IsDefaultForLanguage="True" /><Label Value="C006" Language="1036" IsDefaultForLanguage="False" /><Label Value="Gali" Language="1036" IsDefaultForLanguage="False" /></Labels><Terms></Terms></Term><Term Id="42b1e0a9-82e7-4404-b271-b493688134c7" Name="Pavillon Massey" IsDeprecated="False" IsAvailableForTagging="True" IsKeyword="False" IsReused="False" IsRoot="False" IsSourceTerm="True" CustomSortOrder="False"><Descriptions><Description Language="1033" Value="C024 (0101) PAVILLON MASSEY (ADMINISTRATION)" /></Descriptions><CustomProperties></CustomProperties><LocalCustomProperties></LocalCustomProperties><Labels><Label Value="Pavillon Massey" Language="1036" IsDefaultForLanguage="True" /><Label Value="C024" Language="1036" IsDefaultForLanguage="False" /><Label Value="Massey" Language="1036" IsDefaultForLanguage="False" /></Labels><Terms><Term Id="f6dba21b-88a1-4665-8777-0305db49a1d5" Name="001 - Salle des serveurs" IsDeprecated="False" IsAvailableForTagging="True" IsKeyword="False" IsReused="False" IsRoot="False" IsSourceTerm="True" CustomSortOrder="False"><Descriptions><Description Language="1033" Value="" /></Descriptions><CustomProperties></CustomProperties><LocalCustomProperties></LocalCustomProperties><Labels><Label Value="001 - Salle des serveurs" Language="1036" IsDefaultForLanguage="True" /></Labels><Terms></Terms></Term><Term Id="6d01cc86-ab8d-4ab2-861b-779ca017058a" Name="009 - Service Ti" IsDeprecated="False" IsAvailableForTagging="True" IsKeyword="False" IsReused="False" IsRoot="False" IsSourceTerm="True" CustomSortOrder="False"><Descriptions><Description Language="1033" Value="" /></Descriptions><CustomProperties></CustomProperties><LocalCustomProperties></LocalCustomProperties><Labels><Label Value="009 - Service Ti" Language="1036" IsDefaultForLanguage="True" /></Labels><Terms></Terms></Term><Term Id="0a07afb0-96f6-44e6-90d1-86a61f368102" Name="100 - Salle de direction générale" IsDeprecated="False" IsAvailableForTagging="True" IsKeyword="False" IsReused="False" IsRoot="False" IsSourceTerm="True" CustomSortOrder="False"><Descriptions><Description Language="1033" Value="" /></Descriptions><CustomProperties></CustomProperties><LocalCustomProperties></LocalCustomProperties><Labels><Label Value="100 - Salle de direction générale" Language="1036" IsDefaultForLanguage="True" /></Labels><Terms></Terms></Term><Term Id="1231fcca-5b39-4099-afb5-1a91dded324c" Name="118 - Sall des Ressource humaines" IsDeprecated="False" IsAvailableForTagging="True" IsKeyword="False" IsReused="False" IsRoot="False" IsSourceTerm="True" CustomSortOrder="False"><Descriptions><Description Language="1033" Value="" /></Descriptions><CustomProperties></CustomProperties><LocalCustomProperties></LocalCustomProperties><Labels><Label Value="118 - Sall des Ressource humaines" Language="1036" IsDefaultForLanguage="True" /></Labels><Terms></Terms></Term><Term Id="33fffb03-7e3b-4d11-899a-b2d7dfb017bb" Name="203 - Salle de conférence Chapître Fort St-Jean" IsDeprecated="False" IsAvailableForTagging="True" IsKeyword="False" IsReused="False" IsRoot="False" IsSourceTerm="True" CustomSortOrder="False"><Descriptions><Description Language="1033" Value="" /></Descriptions><CustomProperties></CustomProperties><LocalCustomProperties></LocalCustomProperties><Labels><Label Value="203 - Salle de conférence Chapître Fort St-Jean" Language="1036" IsDefaultForLanguage="True" /></Labels><Terms></Terms></Term></Terms></Term><Term Id="6c0a416c-c281-4bb3-bf17-cd01d1dc32a8" Name="Pavillon Montcalm" IsDeprecated="False" IsAvailableForTagging="True" IsKeyword="False" IsReused="False" IsRoot="False" IsSourceTerm="True" CustomSortOrder="False"><Descriptions><Description Language="1033" Value="C004 (3201) Pavillon Montcalm" /></Descriptions><CustomProperties></CustomProperties><LocalCustomProperties></LocalCustomProperties><Labels><Label Value="Pavillon Montcalm" Language="1036" IsDefaultForLanguage="True" /></Labels><Terms></Terms></Term><Term Id="ca2192e7-d83a-4387-9fcd-fdce6be082bf" Name="Vieux Mess" IsDeprecated="False" IsAvailableForTagging="True" IsKeyword="False" IsReused="False" IsRoot="False" IsSourceTerm="True" CustomSortOrder="False"><Descriptions><Description Language="1033" Value="" /></Descriptions><CustomProperties></CustomProperties><LocalCustomProperties></LocalCustomProperties><Labels><Label Value="Vieux Mess" Language="1036" IsDefaultForLanguage="True" /></Labels><Terms><Term Id="1f177778-3afb-45ad-b353-83aecef82f67" Name="Le richelieu" IsDeprecated="False" IsAvailableForTagging="True" IsKeyword="False" IsReused="False" IsRoot="False" IsSourceTerm="True" CustomSortOrder="False"><Descriptions><Description Language="1033" Value="" /></Descriptions><CustomProperties></CustomProperties><LocalCustomProperties></LocalCustomProperties><Labels><Label Value="Le richelieu" Language="1036" IsDefaultForLanguage="True" /></Labels><Terms></Terms></Term></Terms></Term></Terms></Term><Term Id="bc2439f8-45ce-4ea5-825e-102225637d95" Name="Liste des terrains sportifs" IsDeprecated="False" IsAvailableForTagging="True" IsKeyword="False" IsReused="False" IsRoot="False" IsSourceTerm="True" CustomSortOrder="False"><Descriptions><Description Language="1033" Value="" /></Descriptions><CustomProperties></CustomProperties><LocalCustomProperties></LocalCustomProperties><Labels><Label Value="Liste des terrains sportifs" Language="1036" IsDefaultForLanguage="True" /></Labels><Terms><Term Id="af205024-8d1a-4427-8585-d473a6baad79" Name="#1 Terrain de Football et Terrain de Soccer" IsDeprecated="False" IsAvailableForTagging="True" IsKeyword="False" IsReused="False" IsRoot="False" IsSourceTerm="True" CustomSortOrder="False"><Descriptions><Description Language="1033" Value="" /></Descriptions><CustomProperties></CustomProperties><LocalCustomProperties></LocalCustomProperties><Labels><Label Value="#1 Terrain de Football et Terrain de Soccer" Language="1036" IsDefaultForLanguage="True" /></Labels><Terms></Terms></Term><Term Id="6dcab51e-aac2-4c8b-a4df-c1c83cd2068f" Name="#2 Terrain de Football" IsDeprecated="False" IsAvailableForTagging="True" IsKeyword="False" IsReused="False" IsRoot="False" IsSourceTerm="True" CustomSortOrder="False"><Descriptions><Description Language="1033" Value="" /></Descriptions><CustomProperties></CustomProperties><LocalCustomProperties></LocalCustomProperties><Labels><Label Value="#2 Terrain de Football" Language="1036" IsDefaultForLanguage="True" /></Labels><Terms></Terms></Term><Term Id="2d28618a-1e94-4d78-9800-af94111603c5" Name="#3 Terrain de Football" IsDeprecated="False" IsAvailableForTagging="True" IsKeyword="False" IsReused="False" IsRoot="False" IsSourceTerm="True" CustomSortOrder="False"><Descriptions><Description Language="1033" Value="" /></Descriptions><CustomProperties></CustomProperties><LocalCustomProperties></LocalCustomProperties><Labels><Label Value="#3 Terrain de Football" Language="1036" IsDefaultForLanguage="True" /></Labels><Terms></Terms></Term><Term Id="29e86421-6717-481e-80e5-ee73e336114f" Name="#4 Terrain de Football" IsDeprecated="False" IsAvailableForTagging="True" IsKeyword="False" IsReused="False" IsRoot="False" IsSourceTerm="True" CustomSortOrder="False"><Descriptions><Description Language="1033" Value="" /></Descriptions><CustomProperties></CustomProperties><LocalCustomProperties></LocalCustomProperties><Labels><Label Value="#4 Terrain de Football" Language="1036" IsDefaultForLanguage="True" /></Labels><Terms></Terms></Term><Term Id="cb2a8528-8ae4-4b94-900e-6f8abb2c7c2a" Name="#5 Terrain de Football" IsDeprecated="False" IsAvailableForTagging="True" IsKeyword="False" IsReused="False" IsRoot="False" IsSourceTerm="True" CustomSortOrder="False"><Descriptions><Description Language="1033" Value="" /></Descriptions><CustomProperties></CustomProperties><LocalCustomProperties></LocalCustomProperties><Labels><Label Value="#5 Terrain de Football" Language="1036" IsDefaultForLanguage="True" /></Labels><Terms></Terms></Term><Term Id="ff92fdeb-6804-4943-b725-ee53fb818013" Name="#6 Terrain de Football" IsDeprecated="False" IsAvailableForTagging="True" IsKeyword="False" IsReused="False" IsRoot="False" IsSourceTerm="True" CustomSortOrder="False"><Descriptions><Description Language="1033" Value="" /></Descriptions><CustomProperties></CustomProperties><LocalCustomProperties></LocalCustomProperties><Labels><Label Value="#6 Terrain de Football" Language="1036" IsDefaultForLanguage="True" /></Labels><Terms></Terms></Term><Term Id="61c91171-367e-4c6b-9bc9-ebddfa122b66" Name="2 Patinoires de Deck Hockey" IsDeprecated="False" IsAvailableForTagging="True" IsKeyword="False" IsReused="False" IsRoot="False" IsSourceTerm="True" CustomSortOrder="False"><Descriptions><Description Language="1033" Value="" /></Descriptions><CustomProperties></CustomProperties><LocalCustomProperties></LocalCustomProperties><Labels><Label Value="2 Patinoires de Deck Hockey" Language="1036" IsDefaultForLanguage="True" /></Labels><Terms></Terms></Term><Term Id="dea23149-9835-4289-9874-c6ff23ddd27b" Name="Arrêt de Balle #1" IsDeprecated="False" IsAvailableForTagging="True" IsKeyword="False" IsReused="False" IsRoot="False" IsSourceTerm="True" CustomSortOrder="False"><Descriptions><Description Language="1033" Value="" /></Descriptions><CustomProperties></CustomProperties><LocalCustomProperties></LocalCustomProperties><Labels><Label Value="Arrêt de Balle #1" Language="1036" IsDefaultForLanguage="True" /></Labels><Terms></Terms></Term><Term Id="db01d770-986b-4572-97f9-f2eba31f2464" Name="Arrêt de Balle #2" IsDeprecated="False" IsAvailableForTagging="True" IsKeyword="False" IsReused="False" IsRoot="False" IsSourceTerm="True" CustomSortOrder="False"><Descriptions><Description Language="1033" Value="" /></Descriptions><CustomProperties></CustomProperties><LocalCustomProperties></LocalCustomProperties><Labels><Label Value="Arrêt de Balle #2" Language="1036" IsDefaultForLanguage="True" /></Labels><Terms></Terms></Term><Term Id="0efff458-21eb-4dd1-9bc9-1f65118beecb" Name="Arrêt de Balle #3" IsDeprecated="False" IsAvailableForTagging="True" IsKeyword="False" IsReused="False" IsRoot="False" IsSourceTerm="True" CustomSortOrder="False"><Descriptions><Description Language="1033" Value="" /></Descriptions><CustomProperties></CustomProperties><LocalCustomProperties></LocalCustomProperties><Labels><Label Value="Arrêt de Balle #3" Language="1036" IsDefaultForLanguage="True" /></Labels><Terms></Terms></Term><Term Id="15c4326a-c8e3-4104-84e8-bda6d7ddd018" Name="Tennis 4 Courts" IsDeprecated="False" IsAvailableForTagging="True" IsKeyword="False" IsReused="False" IsRoot="False" IsSourceTerm="True" CustomSortOrder="False"><Descriptions><Description Language="1033" Value="" /></Descriptions><CustomProperties></CustomProperties><LocalCustomProperties></LocalCustomProperties><Labels><Label Value="Tennis 4 Courts" Language="1036" IsDefaultForLanguage="True" /></Labels><Terms></Terms></Term></Terms></Term><Term Id="b2be896c-c293-4b02-8927-2830a939c61b" Name="Rue des Remparts" IsDeprecated="False" IsAvailableForTagging="True" IsKeyword="False" IsReused="False" IsRoot="False" IsSourceTerm="True" CustomSortOrder="False"><Descriptions><Description Language="1033" Value="" /></Descriptions><CustomProperties></CustomProperties><LocalCustomProperties></LocalCustomProperties><Labels><Label Value="Rue des Remparts" Language="1036" IsDefaultForLanguage="True" /></Labels><Terms><Term Id="72b08630-3f4c-4f18-8ee4-3146fda507c9" Name="Central thermique" IsDeprecated="False" IsAvailableForTagging="True" IsKeyword="False" IsReused="False" IsRoot="False" IsSourceTerm="True" CustomSortOrder="False"><Descriptions><Description Language="1033" Value="C102 (5801) CENTRALE THERMIQUE" /></Descriptions><CustomProperties></CustomProperties><LocalCustomProperties></LocalCustomProperties><Labels><Label Value="Central thermique" Language="1036" IsDefaultForLanguage="True" /><Label Value="Bouilloire" Language="1036" IsDefaultForLanguage="False" /><Label Value="C102" Language="1036" IsDefaultForLanguage="False" /></Labels><Terms></Terms></Term><Term Id="8fb5a1c1-d281-41d7-ba0c-e3799e1021b8" Name="Garage" IsDeprecated="False" IsAvailableForTagging="True" IsKeyword="False" IsReused="False" IsRoot="False" IsSourceTerm="True" CustomSortOrder="False"><Descriptions><Description Language="1033" Value="" /></Descriptions><CustomProperties></CustomProperties><LocalCustomProperties></LocalCustomProperties><Labels><Label Value="Garage" Language="1036" IsDefaultForLanguage="True" /></Labels><Terms></Terms></Term><Term Id="243ab7aa-ede2-4d1d-beb0-077796438c88" Name="Musé ancienne prison" IsDeprecated="False" IsAvailableForTagging="True" IsKeyword="False" IsReused="False" IsRoot="False" IsSourceTerm="True" CustomSortOrder="False"><Descriptions><Description Language="1033" Value="C026 (2602) Musée (Ancienne Prison)" /></Descriptions><CustomProperties></CustomProperties><LocalCustomProperties></LocalCustomProperties><Labels><Label Value="Musé ancienne prison" Language="1036" IsDefaultForLanguage="True" /><Label Value="2602" Language="1036" IsDefaultForLanguage="False" /><Label Value="Prison" Language="1036" IsDefaultForLanguage="False" /></Labels><Terms></Terms></Term><Term Id="5bdfcf12-5060-4e07-82c2-8791d11cf1c4" Name="P12" IsDeprecated="False" IsAvailableForTagging="True" IsKeyword="False" IsReused="False" IsRoot="False" IsSourceTerm="True" CustomSortOrder="False"><Descriptions><Description Language="1033" Value="" /></Descriptions><CustomProperties></CustomProperties><LocalCustomProperties></LocalCustomProperties><Labels><Label Value="P12" Language="1036" IsDefaultForLanguage="True" /></Labels><Terms></Terms></Term><Term Id="43a15768-bcd2-484e-b292-05d957548708" Name="P13" IsDeprecated="False" IsAvailableForTagging="True" IsKeyword="False" IsReused="False" IsRoot="False" IsSourceTerm="True" CustomSortOrder="False"><Descriptions><Description Language="1033" Value="" /></Descriptions><CustomProperties></CustomProperties><LocalCustomProperties></LocalCustomProperties><Labels><Label Value="P13" Language="1036" IsDefaultForLanguage="True" /></Labels><Terms></Terms></Term><Term Id="8c588c36-382a-4154-9985-bac26801d668" Name="P14" IsDeprecated="False" IsAvailableForTagging="True" IsKeyword="False" IsReused="False" IsRoot="False" IsSourceTerm="True" CustomSortOrder="False"><Descriptions><Description Language="1033" Value="" /></Descriptions><CustomProperties></CustomProperties><LocalCustomProperties></LocalCustomProperties><Labels><Label Value="P14" Language="1036" IsDefaultForLanguage="True" /></Labels><Terms></Terms></Term><Term Id="3b953f81-d01c-4a0b-9335-084842f36724" Name="P15" IsDeprecated="False" IsAvailableForTagging="True" IsKeyword="False" IsReused="False" IsRoot="False" IsSourceTerm="True" CustomSortOrder="False"><Descriptions><Description Language="1033" Value="" /></Descriptions><CustomProperties></CustomProperties><LocalCustomProperties></LocalCustomProperties><Labels><Label Value="P15" Language="1036" IsDefaultForLanguage="True" /></Labels><Terms></Terms></Term><Term Id="86ac3c46-f683-4b9c-9f9d-1aef8da5861e" Name="P16" IsDeprecated="False" IsAvailableForTagging="True" IsKeyword="False" IsReused="False" IsRoot="False" IsSourceTerm="True" CustomSortOrder="False"><Descriptions><Description Language="1033" Value="" /></Descriptions><CustomProperties></CustomProperties><LocalCustomProperties></LocalCustomProperties><Labels><Label Value="P16" Language="1036" IsDefaultForLanguage="True" /></Labels><Terms></Terms></Term><Term Id="2d653667-b241-4d62-8b11-ccba55ecf8d9" Name="Pavillon Les Forges" IsDeprecated="False" IsAvailableForTagging="True" IsKeyword="False" IsReused="False" IsRoot="False" IsSourceTerm="True" CustomSortOrder="False"><Descriptions><Description Language="1033" Value="C003 (4701) PAVILLON LES FORGES" /></Descriptions><CustomProperties></CustomProperties><LocalCustomProperties></LocalCustomProperties><Labels><Label Value="Pavillon Les Forges" Language="1036" IsDefaultForLanguage="True" /><Label Value="Musé" Language="1036" IsDefaultForLanguage="False" /><Label Value="Musée du Fort Saint-Jean" Language="1036" IsDefaultForLanguage="False" /></Labels><Terms></Terms></Term><Term Id="77d32331-527e-4141-adf1-7b5521db058a" Name="PMQ" IsDeprecated="False" IsAvailableForTagging="True" IsKeyword="False" IsReused="False" IsRoot="False" IsSourceTerm="True" CustomSortOrder="False"><Descriptions><Description Language="1033" Value="" /></Descriptions><CustomProperties></CustomProperties><LocalCustomProperties></LocalCustomProperties><Labels><Label Value="PMQ" Language="1036" IsDefaultForLanguage="True" /></Labels><Terms><Term Id="4ef6ba96-e5fb-485a-ae65-4a405e7d9435" Name="C050" IsDeprecated="False" IsAvailableForTagging="True" IsKeyword="False" IsReused="False" IsRoot="False" IsSourceTerm="True" CustomSortOrder="False"><Descriptions><Description Language="1033" Value="C050 (7001) LOGEMENTS 4, 5, 6, 7" /></Descriptions><CustomProperties></CustomProperties><LocalCustomProperties></LocalCustomProperties><Labels><Label Value="C050" Language="1036" IsDefaultForLanguage="True" /></Labels><Terms><Term Id="a844210c-c15c-4f5e-82f4-eac9374ffa6f" Name="Logements 4" IsDeprecated="False" IsAvailableForTagging="True" IsKeyword="False" IsReused="False" IsRoot="False" IsSourceTerm="True" CustomSortOrder="False"><Descriptions><Description Language="1033" Value="" /></Descriptions><CustomProperties></CustomProperties><LocalCustomProperties></LocalCustomProperties><Labels><Label Value="Logements 4" Language="1036" IsDefaultForLanguage="True" /></Labels><Terms></Terms></Term><Term Id="5ace0dc6-ec95-4aea-a186-608dfbe287ff" Name="Logements 5" IsDeprecated="False" IsAvailableForTagging="True" IsKeyword="False" IsReused="False" IsRoot="False" IsSourceTerm="True" CustomSortOrder="False"><Descriptions><Description Language="1033" Value="" /></Descriptions><CustomProperties></CustomProperties><LocalCustomProperties></LocalCustomProperties><Labels><Label Value="Logements 5" Language="1036" IsDefaultForLanguage="True" /></Labels><Terms></Terms></Term><Term Id="6b961695-2a08-4c7f-bbf7-283331251472" Name="Logements 6" IsDeprecated="False" IsAvailableForTagging="True" IsKeyword="False" IsReused="False" IsRoot="False" IsSourceTerm="True" CustomSortOrder="False"><Descriptions><Description Language="1033" Value="" /></Descriptions><CustomProperties></CustomProperties><LocalCustomProperties></LocalCustomProperties><Labels><Label Value="Logements 6" Language="1036" IsDefaultForLanguage="True" /></Labels><Terms></Terms></Term><Term Id="fa8b5bc6-4f68-42cf-80a7-6e1f5824aded" Name="Logements 7" IsDeprecated="False" IsAvailableForTagging="True" IsKeyword="False" IsReused="False" IsRoot="False" IsSourceTerm="True" CustomSortOrder="False"><Descriptions><Description Language="1033" Value="" /></Descriptions><CustomProperties></CustomProperties><LocalCustomProperties></LocalCustomProperties><Labels><Label Value="Logements 7" Language="1036" IsDefaultForLanguage="True" /></Labels><Terms></Terms></Term></Terms></Term><Term Id="6587eeb4-3431-4f5e-b6be-5afaa1e844aa" Name="C051" IsDeprecated="False" IsAvailableForTagging="True" IsKeyword="False" IsReused="False" IsRoot="False" IsSourceTerm="True" CustomSortOrder="False"><Descriptions><Description Language="1033" Value="C051 (7002) LOGEMENTS 8, 9, 10, 11" /></Descriptions><CustomProperties></CustomProperties><LocalCustomProperties></LocalCustomProperties><Labels><Label Value="C051" Language="1036" IsDefaultForLanguage="True" /></Labels><Terms><Term Id="c25a58c3-57f3-4bc4-b388-5c33ab3b70c6" Name="Logements 10" IsDeprecated="False" IsAvailableForTagging="True" IsKeyword="False" IsReused="False" IsRoot="False" IsSourceTerm="True" CustomSortOrder="False"><Descriptions><Description Language="1033" Value="" /></Descriptions><CustomProperties></CustomProperties><LocalCustomProperties></LocalCustomProperties><Labels><Label Value="Logements 10" Language="1036" IsDefaultForLanguage="True" /></Labels><Terms></Terms></Term><Term Id="21b11bf2-fbd6-43cc-85d3-82d52d2de9e4" Name="Logements 11" IsDeprecated="False" IsAvailableForTagging="True" IsKeyword="False" IsReused="False" IsRoot="False" IsSourceTerm="True" CustomSortOrder="False"><Descriptions><Description Language="1033" Value="" /></Descriptions><CustomProperties></CustomProperties><LocalCustomProperties></LocalCustomProperties><Labels><Label Value="Logements 11" Language="1036" IsDefaultForLanguage="True" /></Labels><Terms></Terms></Term><Term Id="2b9122bb-fe49-4deb-b93b-e8a017ef7f40" Name="Logements 8" IsDeprecated="False" IsAvailableForTagging="True" IsKeyword="False" IsReused="False" IsRoot="False" IsSourceTerm="True" CustomSortOrder="False"><Descriptions><Description Language="1033" Value="" /></Descriptions><CustomProperties></CustomProperties><LocalCustomProperties></LocalCustomProperties><Labels><Label Value="Logements 8" Language="1036" IsDefaultForLanguage="True" /></Labels><Terms></Terms></Term><Term Id="bd3eff8f-0336-4716-9da9-c205e1456aa6" Name="Logements 9" IsDeprecated="False" IsAvailableForTagging="True" IsKeyword="False" IsReused="False" IsRoot="False" IsSourceTerm="True" CustomSortOrder="False"><Descriptions><Description Language="1033" Value="" /></Descriptions><CustomProperties></CustomProperties><LocalCustomProperties></LocalCustomProperties><Labels><Label Value="Logements 9" Language="1036" IsDefaultForLanguage="True" /></Labels><Terms></Terms></Term></Terms></Term><Term Id="2ba2d689-aab9-4782-91a2-97f9baa92160" Name="C052" IsDeprecated="False" IsAvailableForTagging="True" IsKeyword="False" IsReused="False" IsRoot="False" IsSourceTerm="True" CustomSortOrder="False"><Descriptions><Description Language="1033" Value="C052 (7003) LOGEMENTS 12, 13, 14, 15" /></Descriptions><CustomProperties></CustomProperties><LocalCustomProperties></LocalCustomProperties><Labels><Label Value="C052" Language="1036" IsDefaultForLanguage="True" /></Labels><Terms><Term Id="b845105d-431e-4145-a224-bcf43d365250" Name="Logements 12" IsDeprecated="False" IsAvailableForTagging="True" IsKeyword="False" IsReused="False" IsRoot="False" IsSourceTerm="True" CustomSortOrder="False"><Descriptions><Description Language="1033" Value="" /></Descriptions><CustomProperties></CustomProperties><LocalCustomProperties></LocalCustomProperties><Labels><Label Value="Logements 12" Language="1036" IsDefaultForLanguage="True" /></Labels><Terms></Terms></Term><Term Id="afcadcba-cdb1-41e0-9385-17b7762eaa84" Name="Logements 13" IsDeprecated="False" IsAvailableForTagging="True" IsKeyword="False" IsReused="False" IsRoot="False" IsSourceTerm="True" CustomSortOrder="False"><Descriptions><Description Language="1033" Value="" /></Descriptions><CustomProperties></CustomProperties><LocalCustomProperties></LocalCustomProperties><Labels><Label Value="Logements 13" Language="1036" IsDefaultForLanguage="True" /></Labels><Terms></Terms></Term><Term Id="6e63671d-adbe-4729-9cda-d26fc4cd439e" Name="Logements 14" IsDeprecated="False" IsAvailableForTagging="True" IsKeyword="False" IsReused="False" IsRoot="False" IsSourceTerm="True" CustomSortOrder="False"><Descriptions><Description Language="1033" Value="" /></Descriptions><CustomProperties></CustomProperties><LocalCustomProperties></LocalCustomProperties><Labels><Label Value="Logements 14" Language="1036" IsDefaultForLanguage="True" /></Labels><Terms></Terms></Term><Term Id="76ab3dab-e3ad-43c2-9e78-9a37004cbb03" Name="Logements 15" IsDeprecated="False" IsAvailableForTagging="True" IsKeyword="False" IsReused="False" IsRoot="False" IsSourceTerm="True" CustomSortOrder="False"><Descriptions><Description Language="1033" Value="" /></Descriptions><CustomProperties></CustomProperties><LocalCustomProperties></LocalCustomProperties><Labels><Label Value="Logements 15" Language="1036" IsDefaultForLanguage="True" /></Labels><Terms></Terms></Term></Terms></Term></Terms></Term><Term Id="1b8c6d8d-922c-4403-bb23-b70e8d3750a1" Name="Service technique" IsDeprecated="False" IsAvailableForTagging="True" IsKeyword="False" IsReused="False" IsRoot="False" IsSourceTerm="True" CustomSortOrder="False"><Descriptions><Description Language="1033" Value="C102 (9601) SERVICE TECHNIQUE" /></Descriptions><CustomProperties></CustomProperties><LocalCustomProperties></LocalCustomProperties><Labels><Label Value="Service technique" Language="1036" IsDefaultForLanguage="True" /><Label Value="102" Language="1036" IsDefaultForLanguage="False" /><Label Value="C102" Language="1036" IsDefaultForLanguage="False" /></Labels><Terms></Terms></Term></Terms></Term><Term Id="3afa4809-fc58-47df-b8b6-556e5a2460e9" Name="Rue LaSarre" IsDeprecated="False" IsAvailableForTagging="True" IsKeyword="False" IsReused="False" IsRoot="False" IsSourceTerm="True" CustomSortOrder="False"><Descriptions><Description Language="1033" Value="" /></Descriptions><CustomProperties></CustomProperties><LocalCustomProperties></LocalCustomProperties><Labels><Label Value="Rue LaSarre" Language="1036" IsDefaultForLanguage="True" /></Labels><Terms><Term Id="840326fd-a743-465f-9c4f-d27c0439d33a" Name="Pavillon Dextraze" IsDeprecated="False" IsAvailableForTagging="True" IsKeyword="False" IsReused="False" IsRoot="False" IsSourceTerm="True" CustomSortOrder="False"><Descriptions><Description Language="1033" Value="C129 (4600) PAVILLON DEXTRAZE" /></Descriptions><CustomProperties></CustomProperties><LocalCustomProperties></LocalCustomProperties><Labels><Label Value="Pavillon Dextraze" Language="1036" IsDefaultForLanguage="True" /><Label Value="C129" Language="1036" IsDefaultForLanguage="False" /><Label Value="Dex" Language="1036" IsDefaultForLanguage="False" /></Labels><Terms><Term Id="3918d140-e80c-4d6c-8586-556e7552e55a" Name="Cafétéria" IsDeprecated="False" IsAvailableForTagging="True" IsKeyword="False" IsReused="False" IsRoot="False" IsSourceTerm="True" CustomSortOrder="False"><Descriptions><Description Language="1033" Value="" /></Descriptions><CustomProperties></CustomProperties><LocalCustomProperties></LocalCustomProperties><Labels><Label Value="Cafétéria" Language="1036" IsDefaultForLanguage="True" /></Labels><Terms></Terms></Term><Term Id="daa99254-ecc2-4fe3-8272-bc35bda8fb36" Name="Petit Fort" IsDeprecated="False" IsAvailableForTagging="True" IsKeyword="False" IsReused="False" IsRoot="False" IsSourceTerm="True" CustomSortOrder="False"><Descriptions><Description Language="1033" Value="" /></Descriptions><CustomProperties></CustomProperties><LocalCustomProperties></LocalCustomProperties><Labels><Label Value="Petit Fort" Language="1036" IsDefaultForLanguage="True" /></Labels><Terms></Terms></Term><Term Id="3ed37cfb-31ba-4d2a-a8f4-550a4ef5b036" Name="Vieux Fort" IsDeprecated="False" IsAvailableForTagging="True" IsKeyword="False" IsReused="False" IsRoot="False" IsSourceTerm="True" CustomSortOrder="False"><Descriptions><Description Language="1033" Value="" /></Descriptions><CustomProperties></CustomProperties><LocalCustomProperties></LocalCustomProperties><Labels><Label Value="Vieux Fort" Language="1036" IsDefaultForLanguage="True" /></Labels><Terms></Terms></Term><Term Id="8b9ed2e6-5aa1-4636-b462-3e96a3648ce3" Name="Vip" IsDeprecated="False" IsAvailableForTagging="True" IsKeyword="False" IsReused="False" IsRoot="False" IsSourceTerm="True" CustomSortOrder="False"><Descriptions><Description Language="1033" Value="" /></Descriptions><CustomProperties></CustomProperties><LocalCustomProperties></LocalCustomProperties><Labels><Label Value="Vip" Language="1036" IsDefaultForLanguage="True" /></Labels><Terms></Terms></Term></Terms></Term></Terms></Term><Term Id="c6925dde-e0a3-4547-972b-4ee819a327b3" Name="Terrain de Parade" IsDeprecated="False" IsAvailableForTagging="True" IsKeyword="False" IsReused="False" IsRoot="False" IsSourceTerm="True" CustomSortOrder="False"><Descriptions><Description Language="1033" Value="" /></Descriptions><CustomProperties></CustomProperties><LocalCustomProperties></LocalCustomProperties><Labels><Label Value="Terrain de Parade" Language="1036" IsDefaultForLanguage="True" /></Labels><Terms></Terms></Term></Terms></Term></Terms>							
		    			</TermSet><TermSet Id="a33c84be-88c4-4188-ba21-e78b13774e36" Name="Secteur d'activité" Description="" Contact="" IsAvailableForTagging="True" IsOpenForTermCreation="False" CustomSortOrder="34397ede-f233-4cc0-b067-be2ad391a98d:278120a3-7513-4bcc-822d-27139adff803:c7e63418-c1c6-448a-9149-106b4f225d8b:1b905791-4965-4db9-ac5a-0d593e01179d:f60ac8be-3414-43cc-9989-baaeb8eed761"><CustomProperties></CustomProperties>
		    				<Terms><Term Id="34397ede-f233-4cc0-b067-be2ad391a98d" Name="Bâtiments" IsDeprecated="False" IsAvailableForTagging="True" IsKeyword="False" IsReused="False" IsRoot="True" IsSourceTerm="True" CustomSortOrder="9a103d16-7d9b-425a-86dc-e3ad0333be2f:a1932f15-1b46-4a73-9178-4f1b44fc4100:ef34fff4-1e03-43bc-8cd3-bb19ae5fdb10"><Descriptions><Description Language="1033" Value="" /></Descriptions><CustomProperties></CustomProperties><LocalCustomProperties></LocalCustomProperties><Labels><Label Value="Bâtiments" Language="1036" IsDefaultForLanguage="True" /></Labels><Terms><Term Id="9a103d16-7d9b-425a-86dc-e3ad0333be2f" Name="Entretien ménager" IsDeprecated="False" IsAvailableForTagging="True" IsKeyword="False" IsReused="False" IsRoot="False" IsSourceTerm="True" CustomSortOrder="False"><Descriptions><Description Language="1033" Value="" /></Descriptions><CustomProperties></CustomProperties><LocalCustomProperties></LocalCustomProperties><Labels><Label Value="Entretien ménager" Language="1036" IsDefaultForLanguage="True" /></Labels><Terms></Terms></Term><Term Id="a1932f15-1b46-4a73-9178-4f1b44fc4100" Name="Service projets" IsDeprecated="False" IsAvailableForTagging="True" IsKeyword="False" IsReused="False" IsRoot="False" IsSourceTerm="True" CustomSortOrder="False"><Descriptions><Description Language="1033" Value="" /></Descriptions><CustomProperties></CustomProperties><LocalCustomProperties></LocalCustomProperties><Labels><Label Value="Service projets" Language="1036" IsDefaultForLanguage="True" /></Labels><Terms></Terms></Term><Term Id="ef34fff4-1e03-43bc-8cd3-bb19ae5fdb10" Name="Service technique" IsDeprecated="False" IsAvailableForTagging="True" IsKeyword="False" IsReused="False" IsRoot="False" IsSourceTerm="True" CustomSortOrder="False"><Descriptions><Description Language="1033" Value="" /></Descriptions><CustomProperties></CustomProperties><LocalCustomProperties></LocalCustomProperties><Labels><Label Value="Service technique" Language="1036" IsDefaultForLanguage="True" /></Labels><Terms></Terms></Term></Terms></Term><Term Id="278120a3-7513-4bcc-822d-27139adff803" Name="Corporation" IsDeprecated="False" IsAvailableForTagging="True" IsKeyword="False" IsReused="False" IsRoot="True" IsSourceTerm="True" CustomSortOrder="bd0f22be-4c3c-4c70-8cc7-ff4ec7517ca6:e81e6a04-1a74-4789-8a44-f8d34e92f718:688f5ed4-fb5f-4c87-ac8b-8a085c340d68:bd277ccc-8f11-48f6-aa7a-1fd399f1c3a4:896d3910-1812-43a8-a6a9-f1f3ebb78c96:c6aa7b79-bbdd-49a4-9266-151c898d8b44"><Descriptions><Description Language="1033" Value="" /></Descriptions><CustomProperties></CustomProperties><LocalCustomProperties></LocalCustomProperties><Labels><Label Value="Corporation" Language="1036" IsDefaultForLanguage="True" /></Labels><Terms><Term Id="bd0f22be-4c3c-4c70-8cc7-ff4ec7517ca6" Name="Assurance qualité" IsDeprecated="False" IsAvailableForTagging="True" IsKeyword="False" IsReused="False" IsRoot="False" IsSourceTerm="True" CustomSortOrder="False"><Descriptions><Description Language="1033" Value="" /></Descriptions><CustomProperties></CustomProperties><LocalCustomProperties></LocalCustomProperties><Labels><Label Value="Assurance qualité" Language="1036" IsDefaultForLanguage="True" /></Labels><Terms></Terms></Term><Term Id="e81e6a04-1a74-4789-8a44-f8d34e92f718" Name="Comité de direction" IsDeprecated="False" IsAvailableForTagging="True" IsKeyword="False" IsReused="False" IsRoot="False" IsSourceTerm="True" CustomSortOrder="False"><Descriptions><Description Language="1033" Value="" /></Descriptions><CustomProperties></CustomProperties><LocalCustomProperties></LocalCustomProperties><Labels><Label Value="Comité de direction" Language="1036" IsDefaultForLanguage="True" /></Labels><Terms></Terms></Term><Term Id="688f5ed4-fb5f-4c87-ac8b-8a085c340d68" Name="Conseil d’administration" IsDeprecated="False" IsAvailableForTagging="True" IsKeyword="False" IsReused="False" IsRoot="False" IsSourceTerm="True" CustomSortOrder="False"><Descriptions><Description Language="1033" Value="" /></Descriptions><CustomProperties></CustomProperties><LocalCustomProperties></LocalCustomProperties><Labels><Label Value="Conseil d’administration" Language="1036" IsDefaultForLanguage="True" /></Labels><Terms></Terms></Term><Term Id="bd277ccc-8f11-48f6-aa7a-1fd399f1c3a4" Name="Direction générale" IsDeprecated="False" IsAvailableForTagging="True" IsKeyword="False" IsReused="False" IsRoot="False" IsSourceTerm="True" CustomSortOrder="False"><Descriptions><Description Language="1033" Value="" /></Descriptions><CustomProperties></CustomProperties><LocalCustomProperties></LocalCustomProperties><Labels><Label Value="Direction générale" Language="1036" IsDefaultForLanguage="True" /></Labels><Terms></Terms></Term><Term Id="896d3910-1812-43a8-a6a9-f1f3ebb78c96" Name="Documents et archives" IsDeprecated="False" IsAvailableForTagging="True" IsKeyword="False" IsReused="False" IsRoot="False" IsSourceTerm="True" CustomSortOrder="False"><Descriptions><Description Language="1033" Value="" /></Descriptions><CustomProperties></CustomProperties><LocalCustomProperties></LocalCustomProperties><Labels><Label Value="Documents et archives" Language="1036" IsDefaultForLanguage="True" /></Labels><Terms></Terms></Term><Term Id="c6aa7b79-bbdd-49a4-9266-151c898d8b44" Name="Finances" IsDeprecated="False" IsAvailableForTagging="True" IsKeyword="False" IsReused="False" IsRoot="False" IsSourceTerm="True" CustomSortOrder="False"><Descriptions><Description Language="1033" Value="" /></Descriptions><CustomProperties></CustomProperties><LocalCustomProperties></LocalCustomProperties><Labels><Label Value="Finances" Language="1036" IsDefaultForLanguage="True" /></Labels><Terms></Terms></Term></Terms></Term><Term Id="c7e63418-c1c6-448a-9149-106b4f225d8b" Name="Environnement" IsDeprecated="False" IsAvailableForTagging="True" IsKeyword="False" IsReused="False" IsRoot="True" IsSourceTerm="True" CustomSortOrder="4ffa461f-2251-4bb0-a432-b575d10e9ebb:444c5331-3e5c-446e-a4e8-b99eb9ab6448:4092b531-5f67-4290-8725-ad0962df6f3e"><Descriptions><Description Language="1033" Value="" /></Descriptions><CustomProperties></CustomProperties><LocalCustomProperties></LocalCustomProperties><Labels><Label Value="Environnement" Language="1036" IsDefaultForLanguage="True" /></Labels><Terms><Term Id="4ffa461f-2251-4bb0-a432-b575d10e9ebb" Name="Comité environnement" IsDeprecated="False" IsAvailableForTagging="True" IsKeyword="False" IsReused="False" IsRoot="False" IsSourceTerm="True" CustomSortOrder="False"><Descriptions><Description Language="1033" Value="" /></Descriptions><CustomProperties></CustomProperties><LocalCustomProperties></LocalCustomProperties><Labels><Label Value="Comité environnement" Language="1036" IsDefaultForLanguage="True" /></Labels><Terms></Terms></Term><Term Id="444c5331-3e5c-446e-a4e8-b99eb9ab6448" Name="Énergie et environnement" IsDeprecated="False" IsAvailableForTagging="True" IsKeyword="False" IsReused="False" IsRoot="False" IsSourceTerm="True" CustomSortOrder="False"><Descriptions><Description Language="1033" Value="" /></Descriptions><CustomProperties></CustomProperties><LocalCustomProperties></LocalCustomProperties><Labels><Label Value="Énergie et environnement" Language="1036" IsDefaultForLanguage="True" /></Labels><Terms></Terms></Term><Term Id="4092b531-5f67-4290-8725-ad0962df6f3e" Name="Musée du Fort Saint-Jean" IsDeprecated="False" IsAvailableForTagging="True" IsKeyword="False" IsReused="False" IsRoot="False" IsSourceTerm="True" CustomSortOrder="False"><Descriptions><Description Language="1033" Value="" /></Descriptions><CustomProperties></CustomProperties><LocalCustomProperties></LocalCustomProperties><Labels><Label Value="Musée du Fort Saint-Jean" Language="1036" IsDefaultForLanguage="True" /></Labels><Terms></Terms></Term></Terms></Term><Term Id="1b905791-4965-4db9-ac5a-0d593e01179d" Name="Évènements" IsDeprecated="False" IsAvailableForTagging="True" IsKeyword="False" IsReused="False" IsRoot="True" IsSourceTerm="True" CustomSortOrder="1adf825b-3dca-4e92-bfa6-9f0117f83884:642ccb4f-594f-4cf8-a3d3-4aeefbe0e0a0:aa34ec8e-efdd-4130-9d47-b88ff940d140"><Descriptions><Description Language="1033" Value="" /></Descriptions><CustomProperties></CustomProperties><LocalCustomProperties></LocalCustomProperties><Labels><Label Value="Évènements" Language="1036" IsDefaultForLanguage="True" /></Labels><Terms><Term Id="1adf825b-3dca-4e92-bfa6-9f0117f83884" Name="Accueil et hébergement" IsDeprecated="False" IsAvailableForTagging="True" IsKeyword="False" IsReused="False" IsRoot="False" IsSourceTerm="True" CustomSortOrder="False"><Descriptions><Description Language="1033" Value="" /></Descriptions><CustomProperties></CustomProperties><LocalCustomProperties></LocalCustomProperties><Labels><Label Value="Accueil et hébergement" Language="1036" IsDefaultForLanguage="True" /></Labels><Terms></Terms></Term><Term Id="642ccb4f-594f-4cf8-a3d3-4aeefbe0e0a0" Name="Opérations restauration" IsDeprecated="False" IsAvailableForTagging="True" IsKeyword="False" IsReused="False" IsRoot="False" IsSourceTerm="True" CustomSortOrder="False"><Descriptions><Description Language="1033" Value="" /></Descriptions><CustomProperties></CustomProperties><LocalCustomProperties></LocalCustomProperties><Labels><Label Value="Opérations restauration" Language="1036" IsDefaultForLanguage="True" /></Labels><Terms></Terms></Term><Term Id="aa34ec8e-efdd-4130-9d47-b88ff940d140" Name="Service à la clientèle" IsDeprecated="False" IsAvailableForTagging="True" IsKeyword="False" IsReused="False" IsRoot="False" IsSourceTerm="True" CustomSortOrder="False"><Descriptions><Description Language="1033" Value="" /></Descriptions><CustomProperties></CustomProperties><LocalCustomProperties></LocalCustomProperties><Labels><Label Value="Service à la clientèle" Language="1036" IsDefaultForLanguage="True" /></Labels><Terms></Terms></Term></Terms></Term><Term Id="f60ac8be-3414-43cc-9989-baaeb8eed761" Name="Ressources" IsDeprecated="False" IsAvailableForTagging="True" IsKeyword="False" IsReused="False" IsRoot="True" IsSourceTerm="True" CustomSortOrder="9abb491d-7c32-430a-8583-02132a570508:6ea96ec9-3e21-4667-b984-1511125b2a56:872b10c7-f4c8-4b98-ae06-dfafd3fcda23:801cfde2-ccf9-4bbf-9727-c4a685e474b7:47b2d2aa-8d77-4f8c-bace-80a4b9ec21c4"><Descriptions><Description Language="1033" Value="" /></Descriptions><CustomProperties></CustomProperties><LocalCustomProperties></LocalCustomProperties><Labels><Label Value="Ressources" Language="1036" IsDefaultForLanguage="True" /></Labels><Terms><Term Id="9abb491d-7c32-430a-8583-02132a570508" Name="Approvisionnement" IsDeprecated="False" IsAvailableForTagging="True" IsKeyword="False" IsReused="False" IsRoot="False" IsSourceTerm="True" CustomSortOrder="False"><Descriptions><Description Language="1033" Value="" /></Descriptions><CustomProperties></CustomProperties><LocalCustomProperties></LocalCustomProperties><Labels><Label Value="Approvisionnement" Language="1036" IsDefaultForLanguage="True" /></Labels><Terms></Terms></Term><Term Id="6ea96ec9-3e21-4667-b984-1511125b2a56" Name="Comité SST" IsDeprecated="False" IsAvailableForTagging="True" IsKeyword="False" IsReused="False" IsRoot="False" IsSourceTerm="True" CustomSortOrder="False"><Descriptions><Description Language="1033" Value="" /></Descriptions><CustomProperties></CustomProperties><LocalCustomProperties></LocalCustomProperties><Labels><Label Value="Comité SST" Language="1036" IsDefaultForLanguage="True" /></Labels><Terms></Terms></Term><Term Id="872b10c7-f4c8-4b98-ae06-dfafd3fcda23" Name="Ressources humaines" IsDeprecated="False" IsAvailableForTagging="True" IsKeyword="False" IsReused="False" IsRoot="False" IsSourceTerm="True" CustomSortOrder="False"><Descriptions><Description Language="1033" Value="" /></Descriptions><CustomProperties></CustomProperties><LocalCustomProperties></LocalCustomProperties><Labels><Label Value="Ressources humaines" Language="1036" IsDefaultForLanguage="True" /></Labels><Terms></Terms></Term><Term Id="801cfde2-ccf9-4bbf-9727-c4a685e474b7" Name="Sécurité" IsDeprecated="False" IsAvailableForTagging="True" IsKeyword="False" IsReused="False" IsRoot="False" IsSourceTerm="True" CustomSortOrder="False"><Descriptions><Description Language="1033" Value="" /></Descriptions><CustomProperties></CustomProperties><LocalCustomProperties></LocalCustomProperties><Labels><Label Value="Sécurité" Language="1036" IsDefaultForLanguage="True" /></Labels><Terms></Terms></Term><Term Id="47b2d2aa-8d77-4f8c-bace-80a4b9ec21c4" Name="Technologies de l’information" IsDeprecated="False" IsAvailableForTagging="True" IsKeyword="False" IsReused="False" IsRoot="False" IsSourceTerm="True" CustomSortOrder="False"><Descriptions><Description Language="1033" Value="" /></Descriptions><CustomProperties></CustomProperties><LocalCustomProperties></LocalCustomProperties><Labels><Label Value="Technologies de l’information" Language="1036" IsDefaultForLanguage="True" /></Labels><Terms></Terms></Term></Terms></Term></Terms>							
		    			</TermSet></TermSets>
	    		</Group></Groups>	
    	</TermStore>
    </TermStores>
